t3cl/__about__.py
t3cl/__init__.py
t3cl/__main__.py
t3cl-0.0.1.dist-info/DESCRIPTION.rst
t3cl-0.0.1.dist-info/METADATA
t3cl-0.0.1.dist-info/RECORD
t3cl-0.0.1.dist-info/WHEEL
t3cl-0.0.1.dist-info/entry_points.txt
t3cl-0.0.1.dist-info/metadata.json
t3cl-0.0.1.dist-info/top_level.txt
